pdb2py/__init__.py
pdb2py/readpdb.py
pdb2py/libIDL/file_close.pro
pdb2py/libIDL/file_import.pro
pdb2py/libIDL/file_list.pro
pdb2py/libIDL/file_open.pro
pdb2py/libIDL/file_read.pro
pdb2py/libIDL/pdb2idl.pro
pdb2py/libIDL/pdb2idl.so
pdb2py/libIDL/reformat.pro
pdb2py-1.3.data/data/pdb2py/libIDL/file_close.pro
pdb2py-1.3.data/data/pdb2py/libIDL/file_import.pro
pdb2py-1.3.data/data/pdb2py/libIDL/file_list.pro
pdb2py-1.3.data/data/pdb2py/libIDL/file_open.pro
pdb2py-1.3.data/data/pdb2py/libIDL/file_read.pro
pdb2py-1.3.data/data/pdb2py/libIDL/pdb2idl.pro
pdb2py-1.3.data/data/pdb2py/libIDL/pdb2idl.so
pdb2py-1.3.data/data/pdb2py/libIDL/reformat.pro
pdb2py-1.3.dist-info/METADATA
pdb2py-1.3.dist-info/WHEEL
pdb2py-1.3.dist-info/top_level.txt
pdb2py-1.3.dist-info/RECORD
