Metadata-Version: 2.1
Name: pdb2py
Version: 1.3
Summary: Read a pdb file and return a dictionary
Home-page: UNKNOWN
Author: Jerome Guterl
Author-email: guterlj@fusion.gat.com
License: UNKNOWN
Keywords: pdb uedge
Platform: UNKNOWN
Classifier: License :: OSI Approved :: Python Software Foundation License
Requires-Dist: docutils (>=0.3)
Requires-Dist: pidly
